{
  "posts": [
    {
      "id": 1,
      "title": "json-server",
      "author": "typicode"
    },
    {
      "author": "rashmi",
      "message": "lets try agen",
      "time": "19:37",
      "id": 2
    },
    {
      "author": "rashmi",
      "message": "Helo!",
      "time": "19:38",
      "id": 3
    },
    {
      "author": "rashmi",
      "message": "whatspa",
      "time": "19:39",
      "id": 4
    },
    {
      "author": "rashmi",
      "message": "hiii",
      "time": "19:49",
      "id": 5
    },
    {
      "author": "rashmi",
      "message": "pip",
      "time": "19:52",
      "id": 6
    },
    {
      "author": "rashmi",
      "message": "asca",
      "time": "19:53",
      "id": 7
    },
    {
      "author": "rashmi",
      "message": "ascxasc",
      "time": "19:54",
      "id": 8
    },
    {
      "author": "rashmi",
      "message": "cjjbdcsdc",
      "time": "19:55",
      "id": 9
    },
    {
      "author": "rashmi",
      "message": "ccccccccccccccccccc",
      "time": "19:56",
      "id": 10
    },
    {
      "author": "rashmi",
      "message": "scascasc",
      "time": "19:59",
      "id": 11
    },
    {
      "author": "rashmi",
      "message": "casc",
      "time": "19:59",
      "id": 12
    },
    {
      "author": "rashmi",
      "message": "cascc",
      "time": "19:59",
      "id": 13
    },
    {
      "author": "rashmi",
      "message": "ccccc",
      "time": "20:0",
      "id": 14
    },
    {
      "author": "rashmi",
      "message": "cccccccccc",
      "time": "20:0",
      "id": 15
    },
    {
      "author": "rashmi",
      "message": "ccascqaw",
      "time": "20:0",
      "id": 16
    },
    {
      "author": "rashmi",
      "message": "scsdc",
      "time": "20:1",
      "id": 17
    },
    {
      "author": "rashmi",
      "message": "sdcsdc",
      "time": "20:1",
      "id": 18
    },
    {
      "author": "rashmi",
      "message": "dvs",
      "time": "0:9",
      "id": 19
    },
    {
      "author": "rashmi",
      "message": "jk",
      "time": "0:12",
      "id": 20
    },
    {
      "author": "rashmi",
      "message": "casd",
      "time": "0:12",
      "id": 21
    },
    {
      "author": "rashmi",
      "message": "",
      "time": "0:12",
      "id": 22
    },
    {
      "author": "rashmi",
      "message": "vsdfs",
      "time": "0:13",
      "id": 23
    },
    {
      "author": "rashmi",
      "message": "fsdf",
      "time": "0:13",
      "id": 24
    },
    {
      "author": "rashmi",
      "message": "rasg",
      "time": "0:16",
      "id": 25
    },
    {
      "author": "rashmi",
      "message": "f",
      "time": "0:17",
      "id": 26
    },
    {
      "author": "rashmi",
      "message": "pupp",
      "time": "0:18",
      "id": 27
    },
    {
      "author": "rashmi",
      "message": "pip",
      "time": "0:18",
      "id": 28
    },
    {
      "author": "rashmi",
      "message": "k",
      "time": "0:18",
      "id": 29
    },
    {
      "author": "rashmi",
      "message": "dfsdf",
      "time": "0:19",
      "id": 30
    },
    {
      "author": "rashmi",
      "message": "",
      "time": "0:19",
      "id": 31
    },
    {
      "author": "rashmi",
      "message": "",
      "time": "0:19",
      "id": 32
    },
    {
      "author": "rashmi",
      "message": "",
      "time": "0:19",
      "id": 33
    },
    {
      "author": "rashmi",
      "message": "",
      "time": "0:19",
      "id": 34
    },
    {
      "author": "rashmi",
      "message": "",
      "time": "0:19",
      "id": 35
    },
    {
      "author": "rashmi",
      "message": "sdsf",
      "time": "0:25",
      "id": 36
    },
    {
      "author": "rashmi",
      "message": "",
      "time": "0:25",
      "id": 37
    },
    {
      "author": "rashmi",
      "message": "",
      "time": "0:25",
      "id": 38
    },
    {
      "author": "rashmi",
      "message": "df",
      "time": "0:25",
      "id": 39
    },
    {
      "author": "rashmi",
      "message": "",
      "time": "0:25",
      "id": 40
    },
    {
      "author": "rashmi",
      "message": "",
      "time": "0:25",
      "id": 41
    },
    {
      "author": "rashmi",
      "message": "",
      "time": "0:25",
      "id": 42
    },
    {
      "author": "rashmi",
      "message": "",
      "time": "0:25",
      "id": 43
    },
    {
      "author": "rashmi",
      "message": "",
      "time": "0:25",
      "id": 44
    },
    {
      "author": "rashmi",
      "message": "sdf",
      "time": "0:26",
      "id": 45
    },
    {
      "author": "rashmi",
      "message": "dfs",
      "time": "0:33",
      "id": 46
    },
    {
      "author": "rashmi",
      "message": "hjggjhg",
      "time": "0:33",
      "id": 47
    }
  ],
  "comments": [
    {
      "id": 1,
      "body": "some comment",
      "postId": 1
    }
  ],
  "profile": {
    "name": "typicode"
  }
}